arcsightrest.py
setup.cfg
setup.py
arcsightrest.egg-info/PKG-INFO
arcsightrest.egg-info/SOURCES.txt
arcsightrest.egg-info/dependency_links.txt
arcsightrest.egg-info/requires.txt
arcsightrest.egg-info/top_level.txt
arcsightrest.egg-info/zip-safe