Metadata-Version: 1.1
Name: arcsightrest
Version: 1.0
Summary: Python library to connect to the HP Arcsight Logger REST API
Home-page: https://github.com/P1llus/ArcSight-Rest
Author: Marius Iversen
Author-email: marius@chasenet.org
License: MIT
Download-URL: https://github.com/P1llus/ArcSight-Rest/tarball/1.0
Keywords: arcsight,logger,rest
Platform: UNKNOWN
